AUTHORS
COPYING
MANIFEST.in
README.rst
setup.py
shtrihm_fr.egg-info/PKG-INFO
shtrihm_fr.egg-info/SOURCES.txt
shtrihm_fr.egg-info/dependency_links.txt
shtrihm_fr.egg-info/not-zip-safe
shtrihm_fr.egg-info/requires.txt
shtrihm_fr.egg-info/top_level.txt
shtrihmfr/__init__.py
shtrihmfr/conf.py
shtrihmfr/kkt.py
shtrihmfr/protocol.py
shtrihmfr/utils.py