Metadata-Version: 1.1
Name: shtrihm-fr
Version: 0.2.0
Summary: Driver for Shtrih-M cash (fiscal) registers.
Home-page: https://github.com/rosix-ru/shtrihm-fr/
Author: Grigoriy Kramarenko
Author-email: root@rosix.ru
License: GNU General Public License v3 or later (GPLv3+)
Platform: any
Classifier: Development Status :: 3 - Alpha
Classifier: Environment :: Console
Classifier: Intended Audience :: Developers
Classifier: Topic :: Office/Business :: Financial :: Accounting
Classifier: Topic :: Office/Business :: Financial :: Point-Of-Sale
Classifier: Topic :: System :: Hardware :: Hardware Drivers
Classifier: License :: OSI Approved :: GNU General Public License v3 or later (GPLv3+)
Classifier: Natural Language :: Russian
Classifier: Operating System :: OS Independent
Classifier: Programming Language :: Python
Classifier: Programming Language :: Python :: 2.7
